rnet_client/__init__.py
rnet_client/_utils.py
rnet_client-0.0.2.dist-info/METADATA
rnet_client-0.0.2.dist-info/WHEEL
rnet_client-0.0.2.dist-info/RECORD
