Metadata-Version: 2.4
Name: rnet-client
Version: 0.0.2
Summary: rnet client wrapper
Project-URL: Homepage, https://github.com/imbecility/rnet-client
License-Expression: MIT
Classifier: Programming Language :: Python :: 3
Requires-Python: >=3.11
Requires-Dist: rnet>=3.0.0rc20
